{
  "identity.marital_status": "Divorced",
  "identity.full_name_native": "ĐẶNG VĂN HÙNG",
  "contact.postal_code": "550000",
  "contact.phone_primary": "+84 918 350 444",
  "contact.other_phones_used": "No",
  "contact.email": "dangvanhungred@gmail.com",
  "contact.other_emails_used": "Yes",
  "contact.other_emails_history": "dangvanhung@gmail.com",
  "social.platform": "Facebook – Dang Hung",
  "social.identifier": "https://www.facebook.com/hungdang1975",
  "social.other_used": "Yes",
  "social.other_history": "Zalo - Dang Hung",
  "family.father_surname": "N/A",
  "family.mother_surname": "DANG",
  "family.mother_given_names": "THI TIEM",
  "family.mother_name": "DANG THI TIEM",
  "family.mother_date_of_birth": "01 Jan 1954",
  "family.mother_birth_city": "Da Nang",
  "family.mother_birth_country": "Vietnam",
  "family.mother_is_living": "Yes",
  "family.mother_address_line1": "35 An Hai 15 St., An Hai Ward",
  "family.mother_city": "Da Nang",
  "family.mother_postal_code": "550000",
  "family.mother_country": "Vietnam",
  "family.spouse_surname": "N/A",
  "family.spouse_given_names": "",
  "family.previous_spouses_used": "Yes",
  "family.previous_spouses_history": "MAI NGOC HOA | DOB: 19 Jul 1979 | Marriage: 21 Dec 2006 | Divorce: 30 Jul 2025",
  "family.children_used": "Yes",
  "family.children_count": "02",
  "family.children_history": "1) DANG MAI PHUONG THAO | DOB: 02 Apr 2007 | Born: Da Nang, Vietnam | Lives with applicant: No | Address: 4000 East 30th Ave, Eugene, OR 97405, USA | Immigrating: Yes\n2) DANG KHOI NGUYEN | DOB: 04 Aug 2009 | Born: Da Nang, Vietnam | Lives with applicant: No | Address: Room 211, Area A4 Vicoland Apartment Building, Van Don St., Son Tra Ward, Da Nang City, Vietnam 550000 | Immigrating: Yes",
  "travel.us_visited_used": "No",
  "travel.us_visa_issued_used": "No",
  "travel.us_refused_used": "No",
  "employment.primary_occupation": "Freelance Driver",
  "employment.present_employer": "Self-employed",
  "employment.employer_address_line1": "35 An Hai 15 St., An Hai Ward",
  "employment.employer_city": "Da Nang",
  "employment.employer_postal_code": "550000",
  "employment.employer_country": "Vietnam",
  "employment.prior_jobs_10_years_used": "Yes",
  "employment.prior_jobs_history": "1/ 01 Aug 2009 – 31 Mar 2019 | Centeral Area Manager (Remote) | Hoa Linh Pharmaceutical Company Limited | 56 Truong Cong Giai St., Dich Vong Ward, Cau Giay District, Hanoi | Supervisor: Tran Ngoc Anh | +84 243 767 6986\n2/ 01 Jun 2019 – 31 Dec 2019 | Sales Manager | Trung Nam International Pharmaceutical Joint Stock Company | 17 Le Quy Don St., Binh Thuan Ward, Hai Chau District, Da Nang 550000 | Supervisor: Dang Van Nam | +84 903 507 585\n3/ 01 Jan 2021 – 30 Sep 2024 | Real Estate Freelancer | Private owned business | 35 An Hai 15 St., An Hai Bac Ward, Son Tra District, Da Nang 550000\n4/ 01 Oct 2024 – 01 Feb 2025 | Staff | My Hanh Seafood | 03-05 Vo Nguyen Giap St., Phuoc My Ward, Son Tra District, Da Nang 550000 | Supervisor: Tran Ba Linh | +84 799 528 386\n5/ 01 May 2025 – 07 Aug 2025 | Driver | Da Nang Branch - Gsm Green and Smart Mobility JSC | 23 Truong Sa St., Hoa Hai Ward, Ngu Hanh Son District, Da Nang 550000 | Supervisor: Ha Thi Thuy | +84 243 975 6699",
  "education.middle_school_name": "Le Do Secondary School",
  "education.middle_school_address": "82 Nguyen Trung Truc St., An Hai Ward, Son Tra District, Da Nang City, Vietnam 550000",
  "education.middle_school_period": "05 Sep 1986 – 30 May 1990",
  "education.high_school_name": "Hoang Hoa Tham High School",
  "education.high_school_address": "63 Pham Cu Luong St., An Hai Ward, Son Tra District, Da Nang City, Vietnam 550000",
  "education.high_school_period": "05 Sep 1990 – 30 May 1993",
  "education.college_name": "Hanoi Open University",
  "education.college_address": "295 Nguyen Tat Thanh St., Thanh Binh Ward, Hai Chau District, Da Nang City, Vietnam 550000",
  "education.college_major": "Business Administration",
  "education.college_period": "05 Sep 2005 – 14 Oct 2009",
  "additional.military_served_used": "No",
  "additional.other_languages_used": "No",
  "additional.travel_5_years_used": "Yes",
  "additional.travel_5_years_detail": "Lao and Thailand",
  "ssn.applied_before": "No",
  "ssn.want_card_issued": "Yes",
  "ssn.authorize_disclosure": "Yes",
  "security.health_tuberculosis": "No",
  "security.health_vaccinations": "Yes",
  "security.health_mental_disorder": "No",
  "security.health_drug_abuse": "No",
  "security.crime_arrested": "No",
  "security.crime_controlled_substances": "No",
  "security.crime_spouse_drug_trafficking_benefit": "No",
  "security.crime_prostitution": "No",
  "security.crime_money_laundering": "No",
  "security.crime_human_trafficking": "No",
  "security.crime_aid_human_trafficker": "No",
  "security.crime_family_human_trafficking_benefit": "No",
  "security.illegal_activity_us": "No",
  "security.terrorist_activities": "No",
  "security.terrorist_financial_support": "No",
  "security.terrorist_organization_member": "No",
  "security.terrorist_family_support": "No",
  "security.genocide": "No",
  "security.torture": "No",
  "security.extrajudicial_killings": "No",
  "security.child_soldiers": "No",
  "security.religious_freedom_violations": "No",
  "security.totalitarian_party": "No",
  "security.farc_support": "No",
  "security.property_expropriation": "No",
  "security.family_property_expropriation": "No",
  "security.forced_abortion_sterilization": "No",
  "security.chemical_weapons_info": "No",
  "security.family_chemical_weapons_info": "No",
  "security.immigration_fraud": "No",
  "security.deported": "No",
  "security.child_custody_withheld": "No",
  "security.aid_child_custody_withheld": "No",
  "security.illegal_voting": "No",
  "security.renounce_citizenship_tax": "No",
  "security.f_visa_public_school_unpaid": "No",
  "security.uncertified_labor": "No",
  "security.foreign_medical_no_exam": "No",
  "security.healthcare_worker_no_cert": "No",
  "security.permanently_ineligible_citizenship": "No",
  "security.evade_military_service": "No",
  "security.polygamy": "No",
  "security.j_visa_residence_requirement": "No",
  "security.frivolous_asylum": "No",
  "security.public_charge": "No"
}
